svgis/__init__.py
svgis/bounding.py
svgis/cli.py
svgis/dom.py
svgis/draw.py
svgis/errors.py
svgis/graticule.py
svgis/projection.py
svgis/style.py
svgis/svg.py
svgis/svgis.py
svgis/transform.py
svgis/utils.py
svgis-0.5.3.dist-info/entry_points.txt
svgis-0.5.3.dist-info/LICENSE
svgis-0.5.3.dist-info/WHEEL
svgis-0.5.3.dist-info/METADATA
svgis-0.5.3.dist-info/RECORD
