Metadata-Version: 2.1
Name: svgis
Version: 0.5.3
Summary: Create SVG drawings from vector geodata files (SHP, geoJSON, etc).
Home-page: https://github.com/fitnr/svgis
Keywords: svg, gis, geojson, shapefile, cartography, map, geodata
Author: Neil Freeman
Author-email: contact@fakeisthenewreal.org
Classifier: License :: OSI Approved :: GNU General Public License v3 or later (GPLv3+)
Classifier: Intended Audience :: Developers
Classifier: Natural Language :: English
Classifier: Operating System :: Unix
Classifier: Programming Language :: Python :: 3.8
Classifier: Programming Language :: Python :: 3.9
Classifier: Programming Language :: Python :: 3.10
Classifier: Operating System :: OS Independent
Requires-Dist: click>=8,<9
Requires-Dist: pyproj>=2.6
Requires-Dist: fiona>=1.8
Requires-Dist: tinycss2>=1.0.2
Requires-Dist: utm>=0.4.0,<1
Requires-Dist: cssselect>=1.1.0
Requires-Dist: lxml>=4.5.0
Requires-Dist: shapely>=1.5.7 ; extra == "clip"
Requires-Dist: coverage[toml] ; extra == "dev"
Requires-Dist: pylint>2.5.0 ; extra == "dev"
Requires-Dist: sphinx ; extra == "doc"
Requires-Dist: sphinx-rtd-theme ; extra == "doc"
Requires-Dist: numpy ; extra == "numpy"
Requires-Dist: visvalingamwyatt>=0.1.1 ; extra == "simplify"
Provides-Extra: clip
Provides-Extra: dev
Provides-Extra: doc
Provides-Extra: numpy
Provides-Extra: simplify
